{
  "id": "https://musclewiki.com/exercise/trx-jumping-squat",
  "sourceUrl": "https://musclewiki.com/exercise/trx-jumping-squat",
  "slug": "glutes-trx-intermediate-piernas-trx-jumping-squat",
  "name": "TRX Jumping Squat",
  "muscle": "Glutes",
  "musclesSecondary": [],
  "equipment": "TRX",
  "difficulty": "Intermediate",
  "force": "",
  "group": "piernas",
  "steps": [],
  "mediaRefs": {
    "front": {
      "url": "https://media.musclewiki.com/media/uploads/videos/branded/male-trx-jump-squat-front.mp4",
      "kind": "video",
      "gender": "male",
      "angle": "front"
    },
    "side": {
      "url": "https://media.musclewiki.com/media/uploads/videos/branded/male-trx-jump-squat-side.mp4",
      "kind": "video",
      "gender": "male",
      "angle": "side"
    }
  },
  "posterRefs": {
    "front": "https://media.musclewiki.com/media/uploads/og-male-trx-jump-squat-front.jpg",
    "side": "https://media.musclewiki.com/media/uploads/og-male-trx-jump-squat-side.jpg"
  }
}